odoo/addons/shopfloor_rest_log/README.rst
odoo/addons/shopfloor_rest_log/__init__.py
odoo/addons/shopfloor_rest_log/__manifest__.py
odoo/addons/shopfloor_rest_log/hooks.py
odoo/addons/shopfloor_rest_log/components/__init__.py
odoo/addons/shopfloor_rest_log/components/service.py
odoo/addons/shopfloor_rest_log/i18n/es_AR.po
odoo/addons/shopfloor_rest_log/i18n/it.po
odoo/addons/shopfloor_rest_log/i18n/shopfloor_rest_log.pot
odoo/addons/shopfloor_rest_log/models/__init__.py
odoo/addons/shopfloor_rest_log/models/rest_log.py
odoo/addons/shopfloor_rest_log/models/shopfloor_app.py
odoo/addons/shopfloor_rest_log/readme/CONTRIBUTORS.md
odoo/addons/shopfloor_rest_log/readme/DESCRIPTION.md
odoo/addons/shopfloor_rest_log/readme/HISTORY.md
odoo/addons/shopfloor_rest_log/readme/USAGE.md
odoo/addons/shopfloor_rest_log/security/groups.xml
odoo/addons/shopfloor_rest_log/static/description/icon.png
odoo/addons/shopfloor_rest_log/static/description/index.html
odoo/addons/shopfloor_rest_log/views/menus.xml
odoo/addons/shopfloor_rest_log/views/rest_log.xml
odoo/addons/shopfloor_rest_log/views/shopfloor_app.xml
odoo_addon_shopfloor_rest_log-18.0.1.1.0.dist-info/METADATA
odoo_addon_shopfloor_rest_log-18.0.1.1.0.dist-info/WHEEL
odoo_addon_shopfloor_rest_log-18.0.1.1.0.dist-info/top_level.txt
odoo_addon_shopfloor_rest_log-18.0.1.1.0.dist-info/RECORD
